controlnet_aux_voltaml/__init__.py
controlnet_aux_voltaml/util.py
controlnet_aux_voltaml/canny/__init__.py
controlnet_aux_voltaml/hed/__init__.py
controlnet_aux_voltaml/lineart/__init__.py
controlnet_aux_voltaml/lineart_anime/__init__.py
controlnet_aux_voltaml/mediapipe_face/__init__.py
controlnet_aux_voltaml/mediapipe_face/mediapipe_face_common.py
controlnet_aux_voltaml/midas/__init__.py
controlnet_aux_voltaml/midas/api.py
controlnet_aux_voltaml/midas/utils.py
controlnet_aux_voltaml/midas/midas/__init__.py
controlnet_aux_voltaml/midas/midas/base_model.py
controlnet_aux_voltaml/midas/midas/blocks.py
controlnet_aux_voltaml/midas/midas/dpt_depth.py
controlnet_aux_voltaml/midas/midas/midas_net.py
controlnet_aux_voltaml/midas/midas/midas_net_custom.py
controlnet_aux_voltaml/midas/midas/transforms.py
controlnet_aux_voltaml/midas/midas/vit.py
controlnet_aux_voltaml/mlsd/__init__.py
controlnet_aux_voltaml/mlsd/utils.py
controlnet_aux_voltaml/mlsd/models/__init__.py
controlnet_aux_voltaml/mlsd/models/mbv2_mlsd_large.py
controlnet_aux_voltaml/mlsd/models/mbv2_mlsd_tiny.py
controlnet_aux_voltaml/normalbae/__init__.py
controlnet_aux_voltaml/normalbae/nets/NNET.py
controlnet_aux_voltaml/normalbae/nets/__init__.py
controlnet_aux_voltaml/normalbae/nets/baseline.py
controlnet_aux_voltaml/normalbae/nets/submodules/__init__.py
controlnet_aux_voltaml/normalbae/nets/submodules/decoder.py
controlnet_aux_voltaml/normalbae/nets/submodules/encoder.py
controlnet_aux_voltaml/normalbae/nets/submodules/submodules.py
controlnet_aux_voltaml/normalbae/nets/submodules/efficientnet_repo/__init__.py
controlnet_aux_voltaml/normalbae/nets/submodules/efficientnet_repo/caffe2_benchmark.py
controlnet_aux_voltaml/normalbae/nets/submodules/efficientnet_repo/caffe2_validate.py
controlnet_aux_voltaml/normalbae/nets/submodules/efficientnet_repo/hubconf.py
controlnet_aux_voltaml/normalbae/nets/submodules/efficientnet_repo/onnx_export.py
controlnet_aux_voltaml-0.3.2.dist-info/METADATA
controlnet_aux_voltaml-0.3.2.dist-info/WHEEL
controlnet_aux_voltaml-0.3.2.dist-info/top_level.txt
controlnet_aux_voltaml-0.3.2.dist-info/RECORD
